setup.py
shtub/__init__.py
shtub/answer.py
shtub/commandinput.py
shtub/commandstub.py
shtub/execution.py
shtub/fixture.py
shtub/stubconfiguration.py
shtub/testbase.py
shtub.egg-info/PKG-INFO
shtub.egg-info/SOURCES.txt
shtub.egg-info/dependency_links.txt
shtub.egg-info/top_level.txt
shtub.egg-info/zip-safe
shtub/verification/__init__.py
shtub/verification/commandinputverifier.py
shtub/verification/verifierloader.py