Metadata-Version: 1.1
Name: shtub
Version: 0.3.5
Summary: shtub - shell command stub
Home-page: https://github.com/yadt/shtub
Author: Alexander Metzner, Michael Gruber, Maximilien Riehl, Marcel Wolf, Udo Juettner
Author-email: alexander.metzner@gmail.com, aelgru@gmail.com, maximilien.riehl@gmail.com, marcel.wolf@immobilienscout24.de, udo.juettner@gmail.com
License: GNU GPL v3
Platform: UNKNOWN
Classifier: Development Status :: 3 - Alpha
Classifier: Programming Language :: Python
